cut_video/__init__.py
cut_video/cut_video.py
cut_video/f1.py
package/__init__.py
package/cut_video.py
package/dataprocess.py
wtai/__init__.py
wtai/cut_video.py
wtai/wtai.py
wtai-dt/__init__.py
wtai-dt/cut_video.py
wtai-dt/wtai-dt.py
wtai_dt/Demo.py
wtai_dt/__init__.py
wtai_dt/cut_video.py
wtai_dt/wtai_dt.py
wtai_dt/ErrorAnalysis/__init__.py
wtai_dt/ErrorAnalysis/error.py
wtai_dt/GeneratorPerformanceAnalysis/__init__.py
wtai_dt/GeneratorPerformanceAnalysis/generator_performance_analysis.py
wtai_dt/LLM/__init__.py
wtai_dt/PowerGenerationStatistics/__init__.py
wtai_dt/PowerGenerationStatistics/power_generation_statistics.py
wtai_dt/Report/__init__.py
wtai_dt/Report/report.py
wtai_dt/SampleData/__init__.py
wtai_dt/Utility/__init__.py
wtai_dt/Utility/save_data_tool.py
wtai_dt/Utility/utility.py
wtai_dt/YawAnalysis/Yaw.py
wtai_dt/YawAnalysis/YawAnalysis.py
wtai_dt/YawAnalysis/__init__.py
wtai_dt/dataplot/__init__.py
wtai_dt/dataplot/fun.py
wtai_dt/dataprocess/__init__.py
wtai_dt/dataprocess/fun.py
wtai_dt/datareport/__init__.py
wtai_dt/datareport/fun.py
wtai_dt-0.0.11.data/scripts/cut_video.py
wtai_dt-0.0.11.data/scripts/dataprocess.py
wtai_dt-0.0.11.data/scripts/wtai-dt.py
wtai_dt-0.0.11.data/scripts/wtai.py
wtai_dt-0.0.11.data/scripts/wtai_dt.py
wtai_dt-0.0.11.data/scripts/wtaidt.py
wtaidt/__init__.py
wtaidt/cut_video.py
wtaidt/wtai.py
wtaidt/wtaidt.py
wtai_dt-0.0.11.dist-info/LICENCE
wtai_dt-0.0.11.dist-info/METADATA
wtai_dt-0.0.11.dist-info/WHEEL
wtai_dt-0.0.11.dist-info/top_level.txt
wtai_dt-0.0.11.dist-info/RECORD
